sqf/__init__.py
sqf/analyzer.py
sqf/base_interpreter.py
sqf/base_tokenizer.py
sqf/base_type.py
sqf/client.py
sqf/common_expressions.py
sqf/database.py
sqf/exceptions.py
sqf/expressions.py
sqf/expressions_cache.py
sqf/interpreter.py
sqf/interpreter_expressions.py
sqf/interpreter_types.py
sqf/keywords.py
sqf/namespace.py
sqf/parser.py
sqf/parser_exp.py
sqf/parser_types.py
sqf/types.py
sqflint-0.3.2.data/scripts/sqflint.py
sqflint-0.3.2.dist-info/METADATA
sqflint-0.3.2.dist-info/RECORD
sqflint-0.3.2.dist-info/WHEEL
sqflint-0.3.2.dist-info/entry_points.txt
sqflint-0.3.2.dist-info/top_level.txt
